Metadata-Version: 2.1
Name: cogsly
Version: 0.0.1
Summary: Prototype for notebook module system
Home-page: https://github.com/jakekara/cogsly
Author: Jake Kara
Author-email: jake@jakekara.com
License: UNKNOWN
Platform: UNKNOWN
Classifier: Programming Language :: Python :: 3
Classifier: License :: OSI Approved :: MIT License
Classifier: Operating System :: OS Independent
Requires-Python: >=3.6
